odoo/addons/beesdoo_base/README.rst
odoo/addons/beesdoo_base/__init__.py
odoo/addons/beesdoo_base/__manifest__.py
odoo/addons/beesdoo_base/i18n/beesdoo_base.pot
odoo/addons/beesdoo_base/i18n/fr_BE.po
odoo12_addon_beesdoo_base-12.0.2.0.1.99.dev1.dist-info/METADATA
odoo12_addon_beesdoo_base-12.0.2.0.1.99.dev1.dist-info/WHEEL
odoo12_addon_beesdoo_base-12.0.2.0.1.99.dev1.dist-info/top_level.txt
odoo12_addon_beesdoo_base-12.0.2.0.1.99.dev1.dist-info/RECORD
